nautobot_nvdatamodels/__init__.py
nautobot_nvdatamodels/_types.py
nautobot_nvdatamodels/app-config-schema.json
nautobot_nvdatamodels/choices.py
nautobot_nvdatamodels/constants.py
nautobot_nvdatamodels/filter_extensions.py
nautobot_nvdatamodels/filters.py
nautobot_nvdatamodels/forms.py
nautobot_nvdatamodels/models.py
nautobot_nvdatamodels/navigation.py
nautobot_nvdatamodels/py.typed
nautobot_nvdatamodels/signals.py
nautobot_nvdatamodels/tables.py
nautobot_nvdatamodels/template_content.py
nautobot_nvdatamodels/urls.py
nautobot_nvdatamodels/views.py
nautobot_nvdatamodels/api/__init__.py
nautobot_nvdatamodels/api/serializers.py
nautobot_nvdatamodels/api/urls.py
nautobot_nvdatamodels/api/views.py
nautobot_nvdatamodels/migrations/0001_initial.py
nautobot_nvdatamodels/migrations/0002_resourceblock_models.py
nautobot_nvdatamodels/migrations/0003_fix_nvlinkdomainmembership_related_name.py
nautobot_nvdatamodels/migrations/__init__.py
nautobot_nvdatamodels/templates/nautobot_nvdatamodels/device_nvidia.html
nautobot_nvdatamodels/templates/nautobot_nvdatamodels/nvlinkdomain_add_devices.html
nautobot_nvdatamodels/templates/nautobot_nvdatamodels/nvlinkdomain_create.html
nautobot_nvdatamodels/templates/nautobot_nvdatamodels/nvlinkdomain_retrieve.html
nautobot_nvdatamodels/templates/nautobot_nvdatamodels/nvlinkdomainmembership_create.html
nautobot_nvdatamodels/templates/nautobot_nvdatamodels/object_bulk_remove.html
nautobot_nvdatamodels/templates/nautobot_nvdatamodels/resourceblock_add_devices.html
nautobot_nvdatamodels/templates/nautobot_nvdatamodels/resourceblock_retrieve.html
nautobot_nvdatamodels/templates/nautobot_nvdatamodels/resourceblockmembership_create.html
nautobot_nvdatamodels/tests/__init__.py
nautobot_nvdatamodels/tests/fixtures.py
nautobot_nvdatamodels/tests/test_api.py
nautobot_nvdatamodels/tests/test_filters.py
nautobot_nvdatamodels/tests/test_forms.py
nautobot_nvdatamodels/tests/test_models.py
nautobot_nvdatamodels/tests/test_views.py
nautobot_nvdatamodels-0.17.0.dist-info/METADATA
nautobot_nvdatamodels-0.17.0.dist-info/WHEEL
nautobot_nvdatamodels-0.17.0.dist-info/licenses/LICENSE
nautobot_nvdatamodels-0.17.0.dist-info/RECORD
