Metadata-Version: 2.4
Name: nautobot-nvdatamodels
Version: 0.17.0
Summary: A Nautobot app that provides tools for modeling NVIDIA products and resources, such as NVLink domains and compute clusters.
Project-URL: Homepage, https://github.com/NVIDIA/nautobot-app-nvdatamodels
Project-URL: Repository, https://github.com/NVIDIA/nautobot-app-nvdatamodels
Project-URL: Documentation, https://github.com/NVIDIA/nautobot-app-nvdatamodels
Project-URL: Bug Tracker, https://github.com/NVIDIA/nautobot-app-nvdatamodels/issues
Author-email: Austin de Coup-Crank <adecoupcrank@nvidia.com>, Spencer Amann <samann@nvidia.com>, Jon Carelli <jcarelli@nvidia.com>
License: Apache-2.0
License-File: LICENSE
Keywords: nautobot,nautobot-app,nautobot-plugin,nvidia
Classifier: Development Status :: 4 - Beta
Classifier: Intended Audience :: Information Technology
Classifier: Programming Language :: Python :: 3
Classifier: Programming Language :: Python :: 3.10
Classifier: Programming Language :: Python :: 3.11
Classifier: Programming Language :: Python :: 3.12
Classifier: Programming Language :: Python :: 3.13
Requires-Python: <3.13,>=3.10
Requires-Dist: nautobot<3.0.0,>=2.4.20
Requires-Dist: pydantic>=2.0.0
Provides-Extra: dev
Requires-Dist: coverage; extra == 'dev'
Requires-Dist: django-debug-toolbar==5.2.0; extra == 'dev'
Requires-Dist: griffe==1.1.1; extra == 'dev'
Requires-Dist: invoke; extra == 'dev'
Requires-Dist: ipython; extra == 'dev'
Requires-Dist: jsonschema; extra == 'dev'
Requires-Dist: markdown; extra == 'dev'
Requires-Dist: markdown-version-annotations==1.0.1; extra == 'dev'
Requires-Dist: mkdocs-material==9.5.32; extra == 'dev'
Requires-Dist: mkdocs==1.6.0; extra == 'dev'
Requires-Dist: mkdocstrings-python==1.10.8; extra == 'dev'
Requires-Dist: mkdocstrings==0.25.2; extra == 'dev'
Requires-Dist: pylint; extra == 'dev'
Requires-Dist: pylint-django; extra == 'dev'
Requires-Dist: pylint-nautobot; extra == 'dev'
Requires-Dist: ruff==0.5.5; extra == 'dev'
Requires-Dist: selenium; extra == 'dev'
Requires-Dist: splinter; extra == 'dev'
Requires-Dist: to-json-schema; extra == 'dev'
Requires-Dist: toml; extra == 'dev'
Requires-Dist: towncrier~=23.6.0; extra == 'dev'
Requires-Dist: yamllint; extra == 'dev'
